mines/__init__.py
mines/__main__.py
mines/__version__.py
mines/cli.py
mines/game_cli.py
mines/player/__init__.py
mines/player/board.py
mines/player/operation.py
mines/player/player.py
mines/player/player_state.py
mines/presenter/__init__.py
mines/presenter/debugger.py
mines/presenter/game.py
mines/program/__init__.py
mines/program/parser.py
mines/program/program.py
mines/runtime/__init__.py
mines/runtime/command.py
mines/runtime/command_selector.py
mines/runtime/command_type.py
mines/runtime/input_buffer.py
mines/runtime/operation_pointer.py
mines/runtime/output_buffer.py
mines/runtime/runner.py
mines/runtime/runtime_state.py
mines/runtime/stack.py
mines/view/__init__.py
mines/view/ansi.py
mines/view/cli_frame_drawer.py
mines/view/getch.py
mines/view/input_view.py
mines/view/interactive_input_source.py
mines/view/output_view.py
mines/view/player_view.py
mines/view/prompt.py
mines/view/step_result_view.py
mines_esolang-2.0.0.dist-info/METADATA
mines_esolang-2.0.0.dist-info/WHEEL
mines_esolang-2.0.0.dist-info/entry_points.txt
mines_esolang-2.0.0.dist-info/licenses/LICENSE
mines_esolang-2.0.0.dist-info/RECORD
