Metadata-Version: 2.4
Name: mines-esolang
Version: 2.0.0
Summary: An esoteric language inspired by Minesweeper.
Project-URL: Homepage, https://github.com/dnek/mines-esolang
Author-email: DNEK <dnek.app@gmail.com>
License: MIT License
License-File: LICENSE
Keywords: esolang,esoteric,interpreter,mines,minesweeper
Classifier: Development Status :: 5 - Production/Stable
Classifier: Environment :: Console
Classifier: Intended Audience :: Developers
Classifier: Intended Audience :: End Users/Desktop
Classifier: License :: OSI Approved :: MIT License
Classifier: Natural Language :: English
Classifier: Natural Language :: Japanese
Classifier: Operating System :: OS Independent
Classifier: Programming Language :: Python :: 3
Classifier: Topic :: Games/Entertainment :: Puzzle Games
Classifier: Topic :: Software Development :: Interpreters
Requires-Python: >=3.13
